fte/__init__.py
fte/_version.py
fte/config.py
fte/covariance_operator.py
fte/utilities.py
fte/confidence_bands/__init__.py
fte/confidence_bands/bands.py
fte/fitting/__init__.py
fte/fitting/doubly_robust.py
fte/fitting/fitting.py
fte/montypy/__init__.py
fte/montypy/coverage.py
fte/montypy/generic.py
fte/plotting/plotting.py
fte/simulation/__init__.py
fte/simulation/coverage.py
fte/simulation/processes.py
fte/simulation/simulate.py
functe-0.0.2a0.dist-info/LICENSE
functe-0.0.2a0.dist-info/METADATA
functe-0.0.2a0.dist-info/WHEEL
functe-0.0.2a0.dist-info/top_level.txt
functe-0.0.2a0.dist-info/RECORD
