Metadata-Version: 2.1
Name: functe
Version: 0.0.2a0
Summary: Estimation of functional treatment effects
Home-page: https://github.com/timmens/fte
Author: Tim Mensinger
Author-email: tmensinger@uni-bonn.de
License: MIT
Project-URL: Changelog, https://github.com/timmens/fte
Project-URL: Documentation, https://github.com/timmens/fte
Project-URL: Github, https://github.com/timmens/fte
Project-URL: Tracker, https://github.com/timmens/fte/issues
Platform: unix
Platform: linux
Platform: osx
Platform: cygwin
Platform: win32
Classifier: Intended Audience :: Science/Research
Classifier: License :: OSI Approved :: MIT License
Classifier: Operating System :: MacOS :: MacOS X
Classifier: Operating System :: Microsoft :: Windows
Classifier: Operating System :: POSIX
Classifier: Programming Language :: Python :: 3
Classifier: Programming Language :: Python :: 3 :: Only
Requires-Python: >=3.8
License-File: LICENSE
Requires-Dist: numpy
Requires-Dist: pandas
Requires-Dist: pytask
Requires-Dist: scikit-learn
Requires-Dist: scipy
